rpg_namer/Random.py
rpg_namer/__init__.py
rpg_namer/__version__.py
rpg_namer/word_lists.py
rpg_namer-1.0.1.dist-info/LICENSE
rpg_namer-1.0.1.dist-info/METADATA
rpg_namer-1.0.1.dist-info/WHEEL
rpg_namer-1.0.1.dist-info/top_level.txt
rpg_namer-1.0.1.dist-info/RECORD
