Metadata-Version: 2.1
Name: rpg-namer
Version: 1.0.1
Summary: Simple random generator for rpg item names.
Home-page: https://github.com/matthew-palmer/rpg_namer
Author: Matthew Palmer
Author-email: palmer.matthew167@gmail.com
License: MIT License
Platform: UNKNOWN
Classifier: Programming Language :: Python :: 3
Classifier: License :: OSI Approved :: MIT License
Classifier: Operating System :: OS Independent
Requires-Python: >=3.6
